[
  {
    "name": [
      "anticrystalist",
      "kisumis",
      "astronyu"
    ],
    "link": [
      "https:\/\/twitter.com\/anticrystalist",
      "https:\/\/www.instagram.com\/kisumis_\/",
      "https:\/\/www.instagram.com\/astronyu\/"
    ]
  },
  {
    "name": [
      "Aprahnicus",
      "",
      ""
    ],
    "link": [
      "https:\/\/twitter.com\/aprahnicus",
      "",
      ""
    ]
  },
  {
    "name": [
      "Yuururin",
      "",
      ""
    ],
    "link": [
      "",
      "",
      ""
    ]
  },
  {
    "name": [
      "Nats Art Space",
      "",
      ""
    ],
    "link": [
      "",
      "",
      ""
    ]
  },
  {
    "name": [
      "ButtsCrafts",
      "",
      ""
    ],
    "link": [
      "https:\/\/www.instagram.com\/buttscrafts\/",
      "",
      ""
    ]
  },
  {
    "name": [
      "Twisty Loop Creations",
      "",
      ""
    ],
    "link": [
      "",
      "",
      ""
    ]
  },
  {
    "name": [
      "Outer Realms Dice",
      "",
      ""
    ],
    "link": [
      "https:\/\/www.instagram.com\/outer.realms.dice\/",
      "",
      ""
    ]
  },
  {
    "name": [
      "Eightfish",
      "",
      ""
    ],
    "link": [
      "https:\/\/www.instagram.com\/actuallyoctopi\/",
      "",
      ""
    ]
  },
  {
    "name": [
      "Emily Echevarria",
      "",
      ""
    ],
    "link": [
      "https:\/\/twitter.com\/FrenchieFie",
      "",
      ""
    ]
  },
  {
    "name": [
      "Ghostlygoods",
      "Camalilium",
      ""
    ],
    "link": [
      "https:\/\/jaxcels.carrd.co\/",
      "https:\/\/camalilium.carrd.co\/",
      ""
    ]
  },
  {
    "name": [
      "Loonartear",
      "Tnkisu",
      ""
    ],
    "link": [
      "https:\/\/www.instagram.com\/loonartear\/",
      "",
      ""
    ]
  },
  {
    "name": [
      "Superlens",
      "",
      ""
    ],
    "link": [
      "https:\/\/www.instagram.com\/ellenwong_art\/",
      "",
      ""
    ]
  },
  {
    "name": [
      "Zetallis",
      "",
      ""
    ],
    "link": [
      "https:\/\/shop.zetallis.com\/",
      "",
      ""
    ]
  },
  {
    "name": [
      "Adzusai Art",
      "",
      ""
    ],
    "link": [
      "https:\/\/twitter.com\/AdzusaiArt",
      "",
      ""
    ]
  },
  {
    "name": [
      "genieart",
      "",
      ""
    ],
    "link": [
      "https:\/\/www.instagram.com\/genieart",
      "",
      ""
    ]
  },
  {
    "name": [
      "Amour",
      "",
      ""
    ],
    "link": [
      "https:\/\/hyeinjenkang.wixsite.com\/amour",
      "",
      ""
    ]
  },
  {
    "name": [
      "Tenshika",
      "",
      ""
    ],
    "link": [
      "",
      "",
      ""
    ]
  },
  {
    "name": [
      "The Apothekary",
      "",
      ""
    ],
    "link": [
      "https:\/\/www.etsy.com\/shop\/TheApothekary",
      "",
      ""
    ]
  },
  {
    "name": [
      "KYUPLS",
      "",
      ""
    ],
    "link": [
      "https:\/\/tiffanychin.carbonmade.com\/",
      "",
      ""
    ]
  },
  {
    "name": [
      "Uppermind Ink",
      "",
      ""
    ],
    "link": [
      "https:\/\/www.instagram.com\/uppermindink\/",
      "",
      ""
    ]
  },
  {
    "name": [
      "pakeji",
      "",
      ""
    ],
    "link": [
      "https:\/\/sta.sh\/2kektgtici8",
      "",
      ""
    ]
  },
  {
    "name": [
      "khuwun",
      "",
      ""
    ],
    "link": [
      "https:\/\/twitter.com\/khuwun",
      "",
      ""
    ]
  },
  {
    "name": [
      "Lottemp3",
      "",
      ""
    ],
    "link": [
      "https:\/\/www.lotte.studio\/",
      "",
      ""
    ]
  },
  {
    "name": [
      "Chim Arts",
      "",
      ""
    ],
    "link": [
      "",
      "",
      ""
    ]
  },
  {
    "name": [
      "Merrymint",
      "",
      ""
    ],
    "link": [
      "https:\/\/merrymintstore.bigcartel.com\/",
      "",
      ""
    ]
  },
  {
    "name": [
      "Nachoz",
      "",
      ""
    ],
    "link": [
      "https:\/\/www.nachozart.com\/",
      "",
      ""
    ]
  },
  {
    "name": [
      "missdurianne",
      "shim_loo",
      ""
    ],
    "link": [
      "https:\/\/twitter.com\/missdurianne",
      "https:\/\/twitter.com\/shim_loo",
      ""
    ]
  },
  {
    "name": [
      "Artistsan Studio",
      "",
      ""
    ],
    "link": [
      "",
      "",
      ""
    ]
  },
  {
    "name": [
      "Hybrid Night Creations",
      "",
      ""
    ],
    "link": [
      "https:\/\/www.hybridnight.com\/",
      "",
      ""
    ]
  },
  {
    "name": [
      "MiaoYuen",
      "Missdoodlesalot",
      ""
    ],
    "link": [
      "https:\/\/miaoyuen.carrd.co\/",
      "https:\/\/www.etsy.com\/shop\/YuniqueWares?ref=seller-platform-mcnav",
      ""
    ]
  },
  {
    "name": [
      "WOLFGANG INDUSTRIES",
      "",
      ""
    ],
    "link": [
      "",
      "",
      ""
    ]
  },
  {
    "name": [
      "basiatlu",
      "",
      ""
    ],
    "link": [
      "https:\/\/www.instagram.com\/basiatlu\/",
      "",
      ""
    ]
  },
  {
    "name": [
      "Turqlight",
      "",
      ""
    ],
    "link": [
      "",
      "",
      ""
    ]
  },
  {
    "name": [
      "Pitangawang",
      "",
      ""
    ],
    "link": [
      "https:\/\/www.instagram.com\/pitangawang\/",
      "",
      ""
    ]
  },
  {
    "name": [
      "Royally Divine",
      "",
      ""
    ],
    "link": [
      "https:\/\/www.instagram.com\/royallydivine\/",
      "",
      ""
    ]
  },
  {
    "name": [
      "Alberto Maldonado",
      "",
      ""
    ],
    "link": [
      "",
      "",
      ""
    ]
  },
  {
    "name": [
      "Girls Are Scary",
      "",
      ""
    ],
    "link": [
      "",
      "",
      ""
    ]
  },
  {
    "name": [
      "Poison Tragic",
      "",
      ""
    ],
    "link": [
      "https:\/\/poisontragic.com\/",
      "",
      ""
    ]
  },
  {
    "name": [
      "Poppypraise",
      "",
      ""
    ],
    "link": [
      "https:\/\/www.instagram.com\/poppypraise\/",
      "",
      ""
    ]
  },
  {
    "name": [
      "Bubble Tea Penguin",
      "",
      ""
    ],
    "link": [
      "https:\/\/bubbleteapenguin.carrd.co\/",
      "",
      ""
    ]
  },
  {
    "name": [
      "Maliadoodles",
      "",
      ""
    ],
    "link": [
      "https:\/\/www.instagram.com\/maliadoodles\/",
      "",
      ""
    ]
  },
  {
    "name": [
      "pandailee",
      "",
      ""
    ],
    "link": [
      "https:\/\/pandailee.carrd.co\/",
      "",
      ""
    ]
  },
  {
    "name": [
      "InfinityRise1",
      "",
      ""
    ],
    "link": [
      "https:\/\/www.infinityrise.net\/",
      "",
      ""
    ]
  },
  {
    "name": [
      "Requiemofkings",
      "Refreshments",
      ""
    ],
    "link": [
      "https:\/\/requiemofkings.artstation.com\/",
      "https:\/\/refreshmints.carbonmade.com\/",
      ""
    ]
  },
  {
    "name": [
      "o.megano",
      "",
      ""
    ],
    "link": [
      "https:\/\/www.etsy.com\/shop\/moomoomegan",
      "",
      ""
    ]
  },
  {
    "name": [
      "Flight & Fancy Co.",
      "",
      ""
    ],
    "link": [
      "https:\/\/www.flightandfancy.co\/",
      "",
      ""
    ]
  },
  {
    "name": [
      "Fifth Element Pins",
      "",
      ""
    ],
    "link": [
      "https:\/\/fifthelementpins.carrd.co",
      "",
      ""
    ]
  },
  {
    "name": [
      "Blulious",
      "",
      ""
    ],
    "link": [
      "https:\/\/blulious.carbonmade.com\/",
      "",
      ""
    ]
  }
]