[
  {
    "id": "1",
    "people": [
      {
        "name": "Xaviercal Customs and Collectibles",
        "link": "https://www.xaviercalcustomsandcollectibles.com/"
      }
    ]
  },
  {
    "id": "2",
    "people": [
      {
        "name": "cosmicloak",
        "link": "https://www.tiktok.com/@cosmicloak"
      }
    ]
  },
  {
    "id": "3",
    "people": [
      {
        "name": "Pikapanda LLC",
        "link": "https://pikadude.com/"
      }
    ]
  },
  {
    "id": "4",
    "people": [
      {
        "name": "Ben Balmaceda",
        "link": "https://www.instagram.com/benbevoicing/?hl=en"
      }
    ]
  },
  {
    "id": "5",
    "people": [
      {
        "name": "Kayli Mills",
        "link": "https://www.instagram.com/kaylimills/?hl=en"
      }
    ]
  },
  {
    "id": "6",
    "people": [
      {
        "name": "Corina Boettger",
        "link": "https://www.instagram.com/corina.boettger/?hl=en"
      }
    ]
  },
  {
    "id": "7",
    "people": [
      {
        "name": "Lauren Choo",
        "link": "https://www.instagram.com/l4urenchoo/?hl=en"
      }
    ]
  },
  {
    "id": "8",
    "people": [
      {
        "name": "PCTC",
        "link": "https://www.instagram.com/pctcstore/"
      }
    ]
  },
  {
    "id": "9",
    "people": [
      {
        "name": "Waifu Factory",
        "link": "https://www.instagram.com/waifufactory97"
      }
    ]
  }
]